[{"Rk":1,"Player":"Paul Arizin*\\arizipa01","Pos":"SF","Age":33,"Tm":"PHW","G":12,"GS":"","MP":459,"FG":95,"FGA":253,"FG%":0.375,"3P":"","3PA":"","3P%":"","2P":95,"2PA":253,"2P%":0.375,"eFG%":0.375,"FT":88,"FTA":102,"FT%":0.863,"ORB":"","DRB":"","TRB":80,"AST":26,"STL":0,"BLK":0,"TOV":0,"PF":44,"PTS":278,"Impact":0.8366013071895425,"year":1962},{"Rk":2,"Player":"Al Attles\\attleal01","Pos":"PG","Age":25,"Tm":"PHW","G":12,"GS":"","MP":338,"FG":28,"FGA":76,"FG%":0.368,"3P":"","3PA":"","3P%":"","2P":28,"2PA":76,"2P%":0.368,"eFG%":0.368,"FT":17,"FTA":31,"FT%":0.548,"ORB":"","DRB":"","TRB":55,"AST":27,"STL":0,"BLK":0,"TOV":0,"PF":54,"PTS":73,"Impact":0.45857988165680474,"year":1962},{"Rk":3,"Player":"Elgin Baylor*\\bayloel01","Pos":"SF","Age":27,"Tm":"LAL","G":13,"GS":"","MP":571,"FG":186,"FGA":425,"FG%":0.438,"3P":"","3PA":"","3P%":"","2P":186,"2PA":425,"2P%":0.438,"eFG%":0.438,"FT":130,"FTA":168,"FT%":0.774,"ORB":"","DRB":"","TRB":230,"AST":47,"STL":0,"BLK":0,"TOV":0,"PF":45,"PTS":502,"Impact":1.3642732049036776,"year":1962},{"Rk":4,"Player":"Al Bianchi\\biancal01","Pos":"PG","Age":29,"Tm":"SYR","G":5,"GS":"","MP":184,"FG":27,"FGA":69,"FG%":0.391,"3P":"","3PA":"","3P%":"","2P":27,"2PA":69,"2P%":0.391,"eFG%":0.391,"FT":17,"FTA":20,"FT%":0.85,"ORB":"","DRB":"","TRB":26,"AST":18,"STL":0,"BLK":0,"TOV":0,"PF":17,"PTS":71,"Impact":0.625,"year":1962},{"Rk":5,"Player":"Bucky Bockhorn\\bockhbu01","Pos":"SG","Age":28,"Tm":"CIN","G":4,"GS":"","MP":157,"FG":27,"FGA":62,"FG%":0.435,"3P":"","3PA":"","3P%":"","2P":27,"2PA":62,"2P%":0.435,"eFG%":0.435,"FT":14,"FTA":16,"FT%":0.875,"ORB":"","DRB":"","TRB":19,"AST":20,"STL":0,"BLK":0,"TOV":0,"PF":11,"PTS":68,"Impact":0.6815286624203821,"year":1962},{"Rk":6,"Player":"Bob Boozer\\boozebo01","Pos":"PF","Age":24,"Tm":"CIN","G":4,"GS":"","MP":143,"FG":32,"FGA":57,"FG%":0.561,"3P":"","3PA":"","3P%":"","2P":32,"2PA":57,"2P%":0.561,"eFG%":0.561,"FT":9,"FTA":12,"FT%":0.75,"ORB":"","DRB":"","TRB":42,"AST":3,"STL":0,"BLK":0,"TOV":0,"PF":16,"PTS":73,"Impact":0.8251748251748252,"year":1962},{"Rk":7,"Player":"Carl Braun\\braunca01","Pos":"PG","Age":34,"Tm":"BOS","G":6,"GS":"","MP":42,"FG":11,"FGA":28,"FG%":0.393,"3P":"","3PA":"","3P%":"","2P":11,"2PA":28,"2P%":0.393,"eFG%":0.393,"FT":3,"FTA":4,"FT%":0.75,"ORB":"","DRB":"","TRB":7,"AST":2,"STL":0,"BLK":0,"TOV":0,"PF":3,"PTS":25,"Impact":0.8095238095238095,"year":1962},{"Rk":8,"Player":"Joe Buckhalter\\buckhjo01","Pos":"PF","Age":24,"Tm":"CIN","G":4,"GS":"","MP":60,"FG":16,"FGA":38,"FG%":0.421,"3P":"","3PA":"","3P%":"","2P":16,"2PA":38,"2P%":0.421,"eFG%":0.421,"FT":2,"FTA":3,"FT%":0.667,"ORB":"","DRB":"","TRB":22,"AST":4,"STL":0,"BLK":0,"TOV":0,"PF":14,"PTS":34,"Impact":1,"year":1962},{"Rk":9,"Player":"Wilt Chamberlain*\\chambwi01","Pos":"C","Age":25,"Tm":"PHW","G":12,"GS":"","MP":576,"FG":162,"FGA":347,"FG%":0.467,"3P":"","3PA":"","3P%":"","2P":162,"2PA":347,"2P%":0.467,"eFG%":0.467,"FT":96,"FTA":151,"FT%":0.636,"ORB":"","DRB":"","TRB":319,"AST":37,"STL":0,"BLK":0,"TOV":0,"PF":27,"PTS":420,"Impact":1.3472222222222223,"year":1962},{"Rk":10,"Player":"Ed Conlin\\conlied01","Pos":"SG","Age":28,"Tm":"PHW","G":11,"GS":"","MP":86,"FG":9,"FGA":45,"FG%":0.2,"3P":"","3PA":"","3P%":"","2P":9,"2PA":45,"2P%":0.2,"eFG%":0.2,"FT":8,"FTA":13,"FT%":0.615,"ORB":"","DRB":"","TRB":20,"AST":3,"STL":0,"BLK":0,"TOV":0,"PF":14,"PTS":26,"Impact":0.5697674418604651,"year":1962},{"Rk":11,"Player":"Larry Costello\\costela01","Pos":"PG","Age":30,"Tm":"SYR","G":5,"GS":"","MP":167,"FG":22,"FGA":51,"FG%":0.431,"3P":"","3PA":"","3P%":"","2P":22,"2PA":51,"2P%":0.431,"eFG%":0.431,"FT":29,"FTA":33,"FT%":0.879,"ORB":"","DRB":"","TRB":16,"AST":28,"STL":0,"BLK":0,"TOV":0,"PF":21,"PTS":73,"Impact":0.7005988023952096,"year":1962},{"Rk":12,"Player":"Bob Cousy*\\cousybo01","Pos":"PG","Age":33,"Tm":"BOS","G":14,"GS":"","MP":474,"FG":86,"FGA":241,"FG%":0.357,"3P":"","3PA":"","3P%":"","2P":86,"2PA":241,"2P%":0.357,"eFG%":0.357,"FT":52,"FTA":76,"FT%":0.684,"ORB":"","DRB":"","TRB":64,"AST":123,"STL":0,"BLK":0,"TOV":0,"PF":43,"PTS":224,"Impact":0.8670886075949367,"year":1962},{"Rk":13,"Player":"Walter Dukes\\dukeswa01","Pos":"C","Age":31,"Tm":"DET","G":10,"GS":"","MP":347,"FG":39,"FGA":91,"FG%":0.429,"3P":"","3PA":"","3P%":"","2P":39,"2PA":91,"2P%":0.429,"eFG%":0.429,"FT":46,"FTA":61,"FT%":0.754,"ORB":"","DRB":"","TRB":138,"AST":24,"STL":0,"BLK":0,"TOV":0,"PF":52,"PTS":124,"Impact":0.8242074927953891,"year":1962},{"Rk":14,"Player":"Johnny Egan\\eganjo01","Pos":"PG","Age":23,"Tm":"DET","G":5,"GS":"","MP":97,"FG":29,"FGA":62,"FG%":0.468,"3P":"","3PA":"","3P%":"","2P":29,"2PA":62,"2P%":0.468,"eFG%":0.468,"FT":10,"FTA":10,"FT%":1,"ORB":"","DRB":"","TRB":9,"AST":16,"STL":0,"BLK":0,"TOV":0,"PF":8,"PTS":68,"Impact":0.9587628865979382,"year":1962},{"Rk":15,"Player":"Wayne Embry*\\embrywa01","Pos":"C","Age":24,"Tm":"CIN","G":4,"GS":"","MP":128,"FG":14,"FGA":30,"FG%":0.467,"3P":"","3PA":"","3P%":"","2P":14,"2PA":30,"2P%":0.467,"eFG%":0.467,"FT":28,"FTA":36,"FT%":0.778,"ORB":"","DRB":"","TRB":45,"AST":8,"STL":0,"BLK":0,"TOV":0,"PF":17,"PTS":56,"Impact":0.8515625,"year":1962},{"Rk":16,"Player":"Ray Felix\\felixra01","Pos":"C","Age":31,"Tm":"LAL","G":13,"GS":"","MP":242,"FG":29,"FGA":59,"FG%":0.492,"3P":"","3PA":"","3P%":"","2P":29,"2PA":59,"2P%":0.492,"eFG%":0.492,"FT":26,"FTA":38,"FT%":0.684,"ORB":"","DRB":"","TRB":77,"AST":7,"STL":0,"BLK":0,"TOV":0,"PF":39,"PTS":84,"Impact":0.6942148760330579,"year":1962},{"Rk":17,"Player":"Bob Ferry\\ferrybo01","Pos":"C","Age":24,"Tm":"DET","G":9,"GS":"","MP":166,"FG":37,"FGA":81,"FG%":0.457,"3P":"","3PA":"","3P%":"","2P":37,"2PA":81,"2P%":0.457,"eFG%":0.457,"FT":26,"FTA":43,"FT%":0.605,"ORB":"","DRB":"","TRB":41,"AST":13,"STL":0,"BLK":0,"TOV":0,"PF":20,"PTS":100,"Impact":0.927710843373494,"year":1962},{"Rk":18,"Player":"Dave Gambee\\gambeda01","Pos":"SF","Age":24,"Tm":"SYR","G":5,"GS":"","MP":170,"FG":17,"FGA":54,"FG%":0.315,"3P":"","3PA":"","3P%":"","2P":17,"2PA":54,"2P%":0.315,"eFG%":0.315,"FT":22,"FTA":25,"FT%":0.88,"ORB":"","DRB":"","TRB":45,"AST":4,"STL":0,"BLK":0,"TOV":0,"PF":22,"PTS":56,"Impact":0.6176470588235294,"year":1962},{"Rk":19,"Player":"Tom Gola*\\golato01","Pos":"SG","Age":29,"Tm":"PHW","G":9,"GS":"","MP":316,"FG":19,"FGA":70,"FG%":0.271,"3P":"","3PA":"","3P%":"","2P":19,"2PA":70,"2P%":0.271,"eFG%":0.271,"FT":19,"FTA":25,"FT%":0.76,"ORB":"","DRB":"","TRB":74,"AST":24,"STL":0,"BLK":0,"TOV":0,"PF":38,"PTS":57,"Impact":0.49050632911392406,"year":1962},{"Rk":20,"Player":"Joe Graboski\\grabojo01","Pos":"PF","Age":32,"Tm":"SYR","G":4,"GS":"","MP":24,"FG":1,"FGA":7,"FG%":0.143,"3P":"","3PA":"","3P%":"","2P":1,"2PA":7,"2P%":0.143,"eFG%":0.143,"FT":1,"FTA":1,"FT%":1,"ORB":"","DRB":"","TRB":4,"AST":0,"STL":0,"BLK":0,"TOV":0,"PF":3,"PTS":3,"Impact":0.2916666666666667,"year":1962},{"Rk":21,"Player":"Hal Greer*\\greerha01","Pos":"SG","Age":25,"Tm":"SYR","G":1,"GS":"","MP":5,"FG":0,"FGA":0,"FG%":"","3P":"","3PA":"","3P%":"","2P":0,"2PA":0,"2P%":"","eFG%":"","FT":0,"FTA":0,"FT%":"","ORB":"","DRB":"","TRB":0,"AST":0,"STL":0,"BLK":0,"TOV":0,"PF":1,"PTS":0,"Impact":0,"year":1962},{"Rk":22,"Player":"Gene Guarilia\\guarige01","Pos":"SF","Age":24,"Tm":"BOS","G":5,"GS":"","MP":26,"FG":2,"FGA":8,"FG%":0.25,"3P":"","3PA":"","3P%":"","2P":2,"2PA":8,"2P%":0.25,"eFG%":0.25,"FT":2,"FTA":5,"FT%":0.4,"ORB":"","DRB":"","TRB":4,"AST":1,"STL":0,"BLK":0,"TOV":0,"PF":6,"PTS":6,"Impact":0.4230769230769231,"year":1962},{"Rk":23,"Player":"Tom Hawkins\\hawkito01","Pos":"SF","Age":25,"Tm":"LAL","G":13,"GS":"","MP":203,"FG":22,"FGA":61,"FG%":0.361,"3P":"","3PA":"","3P%":"","2P":22,"2PA":61,"2P%":0.361,"eFG%":0.361,"FT":10,"FTA":24,"FT%":0.417,"ORB":"","DRB":"","TRB":66,"AST":19,"STL":0,"BLK":0,"TOV":0,"PF":34,"PTS":54,"Impact":0.6847290640394089,"year":1962},{"Rk":24,"Player":"Tom Heinsohn*\\heinsto01","Pos":"PF","Age":27,"Tm":"BOS","G":14,"GS":"","MP":445,"FG":116,"FGA":291,"FG%":0.399,"3P":"","3PA":"","3P%":"","2P":116,"2PA":291,"2P%":0.399,"eFG%":0.399,"FT":58,"FTA":76,"FT%":0.763,"ORB":"","DRB":"","TRB":115,"AST":34,"STL":0,"BLK":0,"TOV":0,"PF":58,"PTS":290,"Impact":0.9865168539325843,"year":1962},{"Rk":25,"Player":"Bailey Howell*\\howelba01","Pos":"SF","Age":25,"Tm":"DET","G":10,"GS":"","MP":378,"FG":69,"FGA":163,"FG%":0.423,"3P":"","3PA":"","3P%":"","2P":69,"2PA":163,"2P%":0.423,"eFG%":0.423,"FT":62,"FTA":75,"FT%":0.827,"ORB":"","DRB":"","TRB":96,"AST":23,"STL":0,"BLK":0,"TOV":0,"PF":48,"PTS":200,"Impact":0.843915343915344,"year":1962},{"Rk":26,"Player":"Hot Rod Hundley\\hundlho01","Pos":"SG","Age":27,"Tm":"LAL","G":12,"GS":"","MP":187,"FG":7,"FGA":25,"FG%":0.28,"3P":"","3PA":"","3P%":"","2P":7,"2PA":25,"2P%":0.28,"eFG%":0.28,"FT":9,"FTA":12,"FT%":0.75,"ORB":"","DRB":"","TRB":18,"AST":32,"STL":0,"BLK":0,"TOV":0,"PF":27,"PTS":23,"Impact":0.39037433155080214,"year":1962},{"Rk":27,"Player":"Howie Jolliff\\jolifho01","Pos":"PF","Age":23,"Tm":"LAL","G":9,"GS":"","MP":77,"FG":2,"FGA":9,"FG%":0.222,"3P":"","3PA":"","3P%":"","2P":2,"2PA":9,"2P%":0.222,"eFG%":0.222,"FT":8,"FTA":8,"FT%":1,"ORB":"","DRB":"","TRB":28,"AST":7,"STL":0,"BLK":0,"TOV":0,"PF":17,"PTS":12,"Impact":0.6103896103896104,"year":1962},{"Rk":28,"Player":"K.C. Jones*\\joneskc01","Pos":"PG","Age":29,"Tm":"BOS","G":14,"GS":"","MP":329,"FG":44,"FGA":102,"FG%":0.431,"3P":"","3PA":"","3P%":"","2P":44,"2PA":102,"2P%":0.431,"eFG%":0.431,"FT":38,"FTA":53,"FT%":0.717,"ORB":"","DRB":"","TRB":56,"AST":55,"STL":0,"BLK":0,"TOV":0,"PF":50,"PTS":126,"Impact":0.7203647416413373,"year":1962},{"Rk":29,"Player":"Sam Jones*\\jonessa01","Pos":"SG","Age":28,"Tm":"BOS","G":14,"GS":"","MP":504,"FG":123,"FGA":277,"FG%":0.444,"3P":"","3PA":"","3P%":"","2P":123,"2PA":277,"2P%":0.444,"eFG%":0.444,"FT":42,"FTA":60,"FT%":0.7,"ORB":"","DRB":"","TRB":99,"AST":44,"STL":0,"BLK":0,"TOV":0,"PF":30,"PTS":288,"Impact":0.8551587301587301,"year":1962},{"Rk":30,"Player":"Willie Jones\\joneswi01","Pos":"PG","Age":25,"Tm":"DET","G":9,"GS":"","MP":180,"FG":43,"FGA":101,"FG%":0.426,"3P":"","3PA":"","3P%":"","2P":43,"2PA":101,"2P%":0.426,"eFG%":0.426,"FT":13,"FTA":14,"FT%":0.929,"ORB":"","DRB":"","TRB":23,"AST":31,"STL":0,"BLK":0,"TOV":0,"PF":27,"PTS":99,"Impact":0.85,"year":1962},{"Rk":31,"Player":"Red Kerr\\kerrre01","Pos":"C","Age":29,"Tm":"SYR","G":5,"GS":"","MP":193,"FG":41,"FGA":109,"FG%":0.376,"3P":"","3PA":"","3P%":"","2P":41,"2PA":109,"2P%":0.376,"eFG%":0.376,"FT":6,"FTA":8,"FT%":0.75,"ORB":"","DRB":"","TRB":80,"AST":10,"STL":0,"BLK":0,"TOV":0,"PF":15,"PTS":88,"Impact":0.9222797927461139,"year":1962},{"Rk":32,"Player":"Jim Krebs\\krebsji01","Pos":"C","Age":26,"Tm":"LAL","G":11,"GS":"","MP":327,"FG":30,"FGA":90,"FG%":0.333,"3P":"","3PA":"","3P%":"","2P":30,"2PA":90,"2P%":0.333,"eFG%":0.333,"FT":22,"FTA":26,"FT%":0.846,"ORB":"","DRB":"","TRB":102,"AST":21,"STL":0,"BLK":0,"TOV":0,"PF":50,"PTS":82,"Impact":0.6269113149847095,"year":1962},{"Rk":33,"Player":"York Larese\\laresyo01","Pos":"SG","Age":23,"Tm":"PHW","G":9,"GS":"","MP":78,"FG":11,"FGA":35,"FG%":0.314,"3P":"","3PA":"","3P%":"","2P":11,"2PA":35,"2P%":0.314,"eFG%":0.314,"FT":8,"FTA":12,"FT%":0.667,"ORB":"","DRB":"","TRB":19,"AST":5,"STL":0,"BLK":0,"TOV":0,"PF":14,"PTS":30,"Impact":0.6923076923076923,"year":1962},{"Rk":34,"Player":"Rudy LaRusso\\larusru01","Pos":"PF","Age":24,"Tm":"LAL","G":13,"GS":"","MP":461,"FG":57,"FGA":156,"FG%":0.365,"3P":"","3PA":"","3P%":"","2P":57,"2PA":156,"2P%":0.365,"eFG%":0.365,"FT":69,"FTA":91,"FT%":0.758,"ORB":"","DRB":"","TRB":118,"AST":22,"STL":0,"BLK":0,"TOV":0,"PF":51,"PTS":183,"Impact":0.7006507592190889,"year":1962},{"Rk":35,"Player":"George Lee\\leege01","Pos":"SF","Age":25,"Tm":"DET","G":6,"GS":"","MP":50,"FG":10,"FGA":20,"FG%":0.5,"3P":"","3PA":"","3P%":"","2P":10,"2PA":20,"2P%":0.5,"eFG%":0.5,"FT":6,"FTA":7,"FT%":0.857,"ORB":"","DRB":"","TRB":8,"AST":1,"STL":0,"BLK":0,"TOV":0,"PF":6,"PTS":26,"Impact":0.7,"year":1962},{"Rk":36,"Player":"Jim Loscutoff\\loscuji01","Pos":"SF","Age":31,"Tm":"BOS","G":14,"GS":"","MP":212,"FG":31,"FGA":86,"FG%":0.36,"3P":"","3PA":"","3P%":"","2P":31,"2PA":86,"2P%":0.36,"eFG%":0.36,"FT":4,"FTA":10,"FT%":0.4,"ORB":"","DRB":"","TRB":59,"AST":6,"STL":0,"BLK":0,"TOV":0,"PF":59,"PTS":66,"Impact":0.6179245283018868,"year":1962},{"Rk":37,"Player":"Ted Luckenbill\\luckete01","Pos":"PF","Age":22,"Tm":"PHW","G":4,"GS":"","MP":17,"FG":0,"FGA":5,"FG%":0,"3P":"","3PA":"","3P%":"","2P":0,"2PA":5,"2P%":0,"eFG%":0,"FT":2,"FTA":5,"FT%":0.4,"ORB":"","DRB":"","TRB":3,"AST":1,"STL":0,"BLK":0,"TOV":0,"PF":3,"PTS":2,"Impact":0.35294117647058826,"year":1962},{"Rk":38,"Player":"Bob McNeill\\mcneibo01","Pos":"PG","Age":23,"Tm":"LAL","G":5,"GS":"","MP":30,"FG":4,"FGA":7,"FG%":0.571,"3P":"","3PA":"","3P%":"","2P":4,"2PA":7,"2P%":0.571,"eFG%":0.571,"FT":1,"FTA":2,"FT%":0.5,"ORB":"","DRB":"","TRB":6,"AST":5,"STL":0,"BLK":0,"TOV":0,"PF":6,"PTS":9,"Impact":0.6666666666666666,"year":1962},{"Rk":39,"Player":"Tom Meschery\\meschto01","Pos":"PF","Age":23,"Tm":"PHW","G":12,"GS":"","MP":508,"FG":89,"FGA":224,"FG%":0.397,"3P":"","3PA":"","3P%":"","2P":89,"2PA":224,"2P%":0.397,"eFG%":0.397,"FT":63,"FTA":73,"FT%":0.863,"ORB":"","DRB":"","TRB":138,"AST":32,"STL":0,"BLK":0,"TOV":0,"PF":48,"PTS":241,"Impact":0.8090551181102362,"year":1962},{"Rk":40,"Player":"Jackie Moreland\\morelja01","Pos":"PF","Age":23,"Tm":"DET","G":7,"GS":"","MP":96,"FG":17,"FGA":33,"FG%":0.515,"3P":"","3PA":"","3P%":"","2P":17,"2PA":33,"2P%":0.515,"eFG%":0.515,"FT":4,"FTA":7,"FT%":0.571,"ORB":"","DRB":"","TRB":24,"AST":7,"STL":0,"BLK":0,"TOV":0,"PF":22,"PTS":38,"Impact":0.71875,"year":1962},{"Rk":41,"Player":"Paul Neumann\\neumapa01","Pos":"PG","Age":24,"Tm":"SYR","G":5,"GS":"","MP":124,"FG":12,"FGA":29,"FG%":0.414,"3P":"","3PA":"","3P%":"","2P":12,"2PA":29,"2P%":0.414,"eFG%":0.414,"FT":4,"FTA":6,"FT%":0.667,"ORB":"","DRB":"","TRB":17,"AST":14,"STL":0,"BLK":0,"TOV":0,"PF":13,"PTS":28,"Impact":0.47580645161290325,"year":1962},{"Rk":42,"Player":"Bevo Nordmann\\nordmbe01","Pos":"C","Age":22,"Tm":"CIN","G":2,"GS":"","MP":5,"FG":0,"FGA":1,"FG%":0,"3P":"","3PA":"","3P%":"","2P":0,"2PA":1,"2P%":0,"eFG%":0,"FT":0,"FTA":0,"FT%":"","ORB":"","DRB":"","TRB":2,"AST":0,"STL":0,"BLK":0,"TOV":0,"PF":1,"PTS":0,"Impact":0.4,"year":1962},{"Rk":43,"Player":"Don Ohl\\ohldo01","Pos":"SG","Age":25,"Tm":"DET","G":8,"GS":"","MP":317,"FG":71,"FGA":171,"FG%":0.415,"3P":"","3PA":"","3P%":"","2P":71,"2PA":171,"2P%":0.415,"eFG%":0.415,"FT":22,"FTA":27,"FT%":0.815,"ORB":"","DRB":"","TRB":27,"AST":25,"STL":0,"BLK":0,"TOV":0,"PF":22,"PTS":164,"Impact":0.6813880126182965,"year":1962},{"Rk":44,"Player":"Gary Phillips\\phillga01","Pos":"PG","Age":22,"Tm":"BOS","G":6,"GS":"","MP":32,"FG":1,"FGA":16,"FG%":0.063,"3P":"","3PA":"","3P%":"","2P":1,"2PA":16,"2P%":0.063,"eFG%":0.063,"FT":8,"FTA":11,"FT%":0.727,"ORB":"","DRB":"","TRB":3,"AST":1,"STL":0,"BLK":0,"TOV":0,"PF":6,"PTS":10,"Impact":0.4375,"year":1962},{"Rk":45,"Player":"Frank Radovich\\radovfr01","Pos":"F","Age":23,"Tm":"PHW","G":2,"GS":"","MP":12,"FG":1,"FGA":6,"FG%":0.167,"3P":"","3PA":"","3P%":"","2P":1,"2PA":6,"2P%":0.167,"eFG%":0.167,"FT":2,"FTA":4,"FT%":0.5,"ORB":"","DRB":"","TRB":3,"AST":0,"STL":0,"BLK":0,"TOV":0,"PF":2,"PTS":4,"Impact":0.5833333333333334,"year":1962},{"Rk":46,"Player":"Frank Ramsey*\\ramsefr01","Pos":"SG","Age":30,"Tm":"BOS","G":13,"GS":"","MP":210,"FG":39,"FGA":104,"FG%":0.375,"3P":"","3PA":"","3P%":"","2P":39,"2PA":104,"2P%":0.375,"eFG%":0.375,"FT":41,"FTA":45,"FT%":0.911,"ORB":"","DRB":"","TRB":38,"AST":10,"STL":0,"BLK":0,"TOV":0,"PF":38,"PTS":119,"Impact":0.7952380952380952,"year":1962},{"Rk":47,"Player":"Hub Reed\\reedhu01","Pos":"C","Age":25,"Tm":"CIN","G":4,"GS":"","MP":69,"FG":9,"FGA":21,"FG%":0.429,"3P":"","3PA":"","3P%":"","2P":9,"2PA":21,"2P%":0.429,"eFG%":0.429,"FT":3,"FTA":4,"FT%":0.75,"ORB":"","DRB":"","TRB":20,"AST":5,"STL":0,"BLK":0,"TOV":0,"PF":9,"PTS":21,"Impact":0.6666666666666666,"year":1962},{"Rk":48,"Player":"Joe Roberts\\roberjo01","Pos":"PF","Age":25,"Tm":"SYR","G":4,"GS":"","MP":64,"FG":8,"FGA":22,"FG%":0.364,"3P":"","3PA":"","3P%":"","2P":8,"2PA":22,"2P%":0.364,"eFG%":0.364,"FT":10,"FTA":14,"FT%":0.714,"ORB":"","DRB":"","TRB":28,"AST":0,"STL":0,"BLK":0,"TOV":0,"PF":9,"PTS":26,"Impact":0.84375,"year":1962},{"Rk":49,"Player":"Oscar Robertson*\\roberos01","Pos":"PG","Age":23,"Tm":"CIN","G":4,"GS":"","MP":185,"FG":42,"FGA":81,"FG%":0.519,"3P":"","3PA":"","3P%":"","2P":42,"2PA":81,"2P%":0.519,"eFG%":0.519,"FT":31,"FTA":39,"FT%":0.795,"ORB":"","DRB":"","TRB":44,"AST":44,"STL":0,"BLK":0,"TOV":0,"PF":18,"PTS":115,"Impact":1.0972972972972972,"year":1962},{"Rk":50,"Player":"Guy Rodgers*\\rodgegu01","Pos":"PG","Age":26,"Tm":"PHW","G":12,"GS":"","MP":482,"FG":52,"FGA":145,"FG%":0.359,"3P":"","3PA":"","3P%":"","2P":52,"2PA":145,"2P%":0.359,"eFG%":0.359,"FT":35,"FTA":55,"FT%":0.636,"ORB":"","DRB":"","TRB":71,"AST":88,"STL":0,"BLK":0,"TOV":0,"PF":57,"PTS":139,"Impact":0.6182572614107884,"year":1962},{"Rk":51,"Player":"Joe Ruklick\\ruklijo01","Pos":"PF","Age":23,"Tm":"PHW","G":2,"GS":"","MP":8,"FG":1,"FGA":4,"FG%":0.25,"3P":"","3PA":"","3P%":"","2P":1,"2PA":4,"2P%":0.25,"eFG%":0.25,"FT":1,"FTA":2,"FT%":0.5,"ORB":"","DRB":"","TRB":4,"AST":0,"STL":0,"BLK":0,"TOV":0,"PF":2,"PTS":3,"Impact":0.875,"year":1962},{"Rk":52,"Player":"Bill Russell*\\russebi01","Pos":"C","Age":27,"Tm":"BOS","G":14,"GS":"","MP":672,"FG":116,"FGA":253,"FG%":0.458,"3P":"","3PA":"","3P%":"","2P":116,"2PA":253,"2P%":0.458,"eFG%":0.458,"FT":82,"FTA":113,"FT%":0.726,"ORB":"","DRB":"","TRB":370,"AST":70,"STL":0,"BLK":0,"TOV":0,"PF":49,"PTS":314,"Impact":1.1220238095238095,"year":1962},{"Rk":53,"Player":"Tom Sanders*\\sandeto01","Pos":"SF","Age":23,"Tm":"BOS","G":14,"GS":"","MP":439,"FG":56,"FGA":130,"FG%":0.431,"3P":"","3PA":"","3P%":"","2P":56,"2PA":130,"2P%":0.431,"eFG%":0.431,"FT":29,"FTA":36,"FT%":0.806,"ORB":"","DRB":"","TRB":115,"AST":14,"STL":0,"BLK":0,"TOV":0,"PF":65,"PTS":141,"Impact":0.6150341685649203,"year":1962},{"Rk":54,"Player":"Dolph Schayes*\\schaydo01","Pos":"PF","Age":33,"Tm":"SYR","G":5,"GS":"","MP":95,"FG":24,"FGA":66,"FG%":0.364,"3P":"","3PA":"","3P%":"","2P":24,"2PA":66,"2P%":0.364,"eFG%":0.364,"FT":9,"FTA":13,"FT%":0.692,"ORB":"","DRB":"","TRB":35,"AST":5,"STL":0,"BLK":0,"TOV":0,"PF":21,"PTS":57,"Impact":1.0210526315789474,"year":1962},{"Rk":55,"Player":"Ray Scott\\scottra01","Pos":"PF","Age":23,"Tm":"DET","G":10,"GS":"","MP":400,"FG":69,"FGA":170,"FG%":0.406,"3P":"","3PA":"","3P%":"","2P":69,"2PA":170,"2P%":0.406,"eFG%":0.406,"FT":35,"FTA":67,"FT%":0.522,"ORB":"","DRB":"","TRB":145,"AST":43,"STL":0,"BLK":0,"TOV":0,"PF":39,"PTS":173,"Impact":0.9025,"year":1962},{"Rk":56,"Player":"Frank Selvy\\selvyfr01","Pos":"SG","Age":29,"Tm":"LAL","G":13,"GS":"","MP":478,"FG":66,"FGA":152,"FG%":0.434,"3P":"","3PA":"","3P%":"","2P":66,"2PA":152,"2P%":0.434,"eFG%":0.434,"FT":33,"FTA":39,"FT%":0.846,"ORB":"","DRB":"","TRB":73,"AST":65,"STL":0,"BLK":0,"TOV":0,"PF":34,"PTS":165,"Impact":0.6338912133891214,"year":1962},{"Rk":57,"Player":"Lee Shaffer\\shaffle01","Pos":"SF","Age":22,"Tm":"SYR","G":5,"GS":"","MP":174,"FG":35,"FGA":99,"FG%":0.354,"3P":"","3PA":"","3P%":"","2P":35,"2PA":99,"2P%":0.354,"eFG%":0.354,"FT":24,"FTA":31,"FT%":0.774,"ORB":"","DRB":"","TRB":55,"AST":7,"STL":0,"BLK":0,"TOV":0,"PF":17,"PTS":94,"Impact":0.896551724137931,"year":1962},{"Rk":58,"Player":"Gene Shue\\shuege01","Pos":"PG","Age":30,"Tm":"DET","G":10,"GS":"","MP":369,"FG":62,"FGA":151,"FG%":0.411,"3P":"","3PA":"","3P%":"","2P":62,"2PA":151,"2P%":0.411,"eFG%":0.411,"FT":37,"FTA":48,"FT%":0.771,"ORB":"","DRB":"","TRB":30,"AST":49,"STL":0,"BLK":0,"TOV":0,"PF":29,"PTS":161,"Impact":0.6504065040650406,"year":1962},{"Rk":59,"Player":"Adrian Smith\\smithad01","Pos":"SG","Age":25,"Tm":"CIN","G":4,"GS":"","MP":53,"FG":8,"FGA":19,"FG%":0.421,"3P":"","3PA":"","3P%":"","2P":8,"2PA":19,"2P%":0.421,"eFG%":0.421,"FT":5,"FTA":5,"FT%":1,"ORB":"","DRB":"","TRB":5,"AST":3,"STL":0,"BLK":0,"TOV":0,"PF":2,"PTS":21,"Impact":0.5471698113207547,"year":1962},{"Rk":60,"Player":"Jack Twyman*\\twymaja01","Pos":"SF","Age":27,"Tm":"CIN","G":4,"GS":"","MP":149,"FG":34,"FGA":78,"FG%":0.436,"3P":"","3PA":"","3P%":"","2P":34,"2PA":78,"2P%":0.436,"eFG%":0.436,"FT":8,"FTA":8,"FT%":1,"ORB":"","DRB":"","TRB":29,"AST":12,"STL":0,"BLK":0,"TOV":0,"PF":18,"PTS":76,"Impact":0.785234899328859,"year":1962},{"Rk":61,"Player":"Jerry West*\\westje01","Pos":"PG","Age":23,"Tm":"LAL","G":13,"GS":"","MP":557,"FG":144,"FGA":310,"FG%":0.465,"3P":"","3PA":"","3P%":"","2P":144,"2PA":310,"2P%":0.465,"eFG%":0.465,"FT":121,"FTA":150,"FT%":0.807,"ORB":"","DRB":"","TRB":88,"AST":57,"STL":0,"BLK":0,"TOV":0,"PF":38,"PTS":409,"Impact":0.9946140035906643,"year":1962},{"Rk":62,"Player":"Bob Wiesenhahn\\wiesebo01","Pos":"SF","Age":23,"Tm":"CIN","G":2,"GS":"","MP":6,"FG":1,"FGA":4,"FG%":0.25,"3P":"","3PA":"","3P%":"","2P":1,"2PA":4,"2P%":0.25,"eFG%":0.25,"FT":1,"FTA":1,"FT%":1,"ORB":"","DRB":"","TRB":2,"AST":0,"STL":0,"BLK":0,"TOV":0,"PF":0,"PTS":3,"Impact":0.8333333333333334,"year":1962},{"Rk":63,"Player":"Wayne Yates\\yateswa01","Pos":"C","Age":24,"Tm":"LAL","G":4,"GS":"","MP":12,"FG":3,"FGA":8,"FG%":0.375,"3P":"","3PA":"","3P%":"","2P":3,"2PA":8,"2P%":0.375,"eFG%":0.375,"FT":1,"FTA":2,"FT%":0.5,"ORB":"","DRB":"","TRB":5,"AST":1,"STL":0,"BLK":0,"TOV":0,"PF":2,"PTS":7,"Impact":1.0833333333333333,"year":1962},{"Rk":64,"Player":"Dave Zeller\\zelleda01","Pos":"PG","Age":22,"Tm":"CIN","G":2,"GS":"","MP":5,"FG":1,"FGA":2,"FG%":0.5,"3P":"","3PA":"","3P%":"","2P":1,"2PA":2,"2P%":0.5,"eFG%":0.5,"FT":0,"FTA":0,"FT%":"","ORB":"","DRB":"","TRB":1,"AST":1,"STL":0,"BLK":0,"TOV":0,"PF":0,"PTS":2,"Impact":0.8,"year":1962}]